{
    "served": 48,
    "dropped": 2,
    "makespan": 8033.833442689554,
    "routing_tree": "(add RT0 (sub (mul (mul RT2 RT3) RT2) (mul RT2 (sub RT3 (max RT0 RT2)))))",
    "sequencing_tree": "ST1",
    "vehicles": [
        {
            "id": 1,
            "type": "TRUCK",
            "routes": [
                [
                    15,
                    40,
                    18,
                    24,
                    11,
                    4
                ],
                [
                    33,
                    2,
                    20,
                    43,
                    9,
                    48,
                    22,
                    31
                ]
            ],
            "makespan": 7776.595205463434
        },
        {
            "id": 2,
            "type": "TRUCK",
            "routes": [
                [
                    16,
                    26,
                    49,
                    44,
                    14,
                    46
                ],
                [
                    6,
                    28,
                    3,
                    21,
                    30,
                    35,
                    34,
                    7
                ]
            ],
            "makespan": 7764.862448323842
        },
        {
            "id": 3,
            "type": "TRUCK",
            "routes": [
                [
                    36,
                    38,
                    10,
                    32,
                    45,
                    23,
                    47,
                    8,
                    17,
                    1
                ],
                [
                    37,
                    12,
                    41
                ]
            ],
            "makespan": 8033.833442689554
        },
        {
            "id": 4,
            "type": "DRONE",
            "routes": [
                [
                    25,
                    13
                ]
            ],
            "makespan": 681.5883900979079
        },
        {
            "id": 5,
            "type": "DRONE",
            "routes": [
                [
                    29,
                    42,
                    27
                ]
            ],
            "makespan": 3335.161155023143
        },
        {
            "id": 6,
            "type": "DRONE",
            "routes": [
                [
                    50,
                    39
                ]
            ],
            "makespan": 2004.8011660199613
        }
    ]
}